airflow_edw_grants/__init__.py
airflow_edw_grants/plugins/__init__.py
airflow_edw_grants/plugins/edw_grants.py
airflow_edw_grants/plugins/templates/add_role.html
airflow_edw_grants/plugins/templates/add_user.html
airflow_edw_grants/plugins/templates/edit_role.html
airflow_edw_grants/plugins/templates/edit_user.html
airflow_edw_grants/plugins/templates/edw_grants.html
airflow_edw_grants-0.1.2.dist-info/LICENSE
airflow_edw_grants-0.1.2.dist-info/METADATA
airflow_edw_grants-0.1.2.dist-info/NOTICE
airflow_edw_grants-0.1.2.dist-info/WHEEL
airflow_edw_grants-0.1.2.dist-info/entry_points.txt
airflow_edw_grants-0.1.2.dist-info/RECORD
