Metadata-Version: 2.3
Name: airflow-edw-grants
Version: 0.1.2
Summary: An Apache Airflow plugin for managing users and roles in an Enterprise Data Warehouse (EDW) and establishing connections between them, specifically for Amazon Redshift.
License: MIT
Author: Hipposys
Requires-Python: >=3.10,<4.0
Classifier: License :: OSI Approved :: MIT License
Classifier: Programming Language :: Python :: 3
Classifier: Programming Language :: Python :: 3.10
Classifier: Programming Language :: Python :: 3.11
Classifier: Programming Language :: Python :: 3.12
Classifier: Programming Language :: Python :: 3.13
Requires-Dist: SQLAlchemy (>=1.4.0)
Requires-Dist: apache-airflow (>=2.4.0,<3.0.0)
Requires-Dist: pandas (>=1.3.5)
Requires-Dist: sqlalchemy-redshift (>=0.8.11)
Project-URL: homepage, https://github.com/hipposys-ltd/airflow-edw-grants
